aiger_dfa/__init__.py
aiger_dfa/aig2dfa.py
aiger_dfa/dfa2aig.py
aiger_dfa/test_aig2dfa.py
aiger_dfa/test_dfa2aig.py
aiger_dfa/utils.py
py_aiger_dfa-0.4.4.dist-info/LICENSE
py_aiger_dfa-0.4.4.dist-info/METADATA
py_aiger_dfa-0.4.4.dist-info/WHEEL
py_aiger_dfa-0.4.4.dist-info/RECORD
