Metadata-Version: 2.1
Name: py-aiger-dfa
Version: 0.4.4
Summary: Library for moving between sequential circuits AIGs and DFAs.
Home-page: https://github.com/mvcisback/py-aiger-dfa
License: MIT
Author: Marcell Vazquez-Chanlatte
Author-email: mvc@linux.com
Requires-Python: >=3.9,<4.0
Classifier: License :: OSI Approved :: MIT License
Classifier: Programming Language :: Python :: 3
Classifier: Programming Language :: Python :: 3.9
Classifier: Programming Language :: Python :: 3.10
Classifier: Programming Language :: Python :: 3.11
Classifier: Programming Language :: Python :: 3.12
Requires-Dist: attrs (>=22)
Requires-Dist: bidict (>=0.22.0,<0.23.0)
Requires-Dist: dfa (>=4,<5)
Requires-Dist: funcy (>=1.12,<2.0)
Requires-Dist: py-aiger (>=6.0.0,<7.0.0)
Requires-Dist: py-aiger-bv (>=4.7.6,<5.0.0)
Requires-Dist: py-aiger-ptltl (>=3.0.0,<4.0.0)
Requires-Dist: pyrsistent (>=0.19,<0.20)
Project-URL: Repository, https://github.com/mvcisback/py-aiger-dfa
